MANIFEST.in
README.txt
setup.cfg
setup.py
VedicCityNames/Language.py
VedicCityNames/NameTranslator.py
VedicCityNames/NameTranslator_test.py
VedicCityNames/TranslateData.yml
VedicCityNames/__init__.py
VedicCityNames.egg-info/PKG-INFO
VedicCityNames.egg-info/SOURCES.txt
VedicCityNames.egg-info/dependency_links.txt
VedicCityNames.egg-info/not-zip-safe
VedicCityNames.egg-info/requires.txt
VedicCityNames.egg-info/top_level.txt