Metadata-Version: 1.0
Name: VedicCityNames
Version: 0.2.3
Summary: Translates current city names in India to their original names
Home-page: http://github.com/muditjai/Python.git/Distribution/VedicCityNames
Author: muditjai
Author-email: muditjai@gmail.com
License: MIT
Platform: UNKNOWN
